{
  "name": "KovoBroza",
  "username": "kovobroza",
  "id": "77680374595",
  "category": null,
  "business_category": "None",
  "phone": null,
  "email": null,
  "bio": "",
  "bio_links": [],
  "homepage": null,
  "followers": 2,
  "follows": 1,
  "facebook_id": "17841477717870046",
  "is_private": false,
  "is_verified": false,
  "profile_image": "https://scontent.cdninstagram.com/v/t51.82787-19/572133055_17846880645590596_933288793440981692_n.jpg?stp=dst-jpg_s320x320_tt6&efg=eyJ2ZW5jb2RlX3RhZyI6InByb2ZpbGVfcGljLmRqYW5nby44NTQuYzIifQ&_nc_ht=scontent.cdninstagram.com&_nc_cat=104&_nc_oc=Q6cZ2gHEEnt1sOOSpcINM1TXAOx1S3ZIH4SDJjc58-m4Nal_QQ02pVNToV6-RIJiYvyi1zo&_nc_ohc=O7FiKIfsND0Q7kNvwF2TVJG&_nc_gid=1JW0i4SECoyBUHsP-g8j9g&edm=AOQ1c0wBAAAA&ccb=7-5&oh=00_AQD_g2PQbucunAv3B_7qhrLLcxLYgWJLk4UxJ7vlThcycg&oe=6A5CC93A&_nc_sid=8b3546",
  "video_count": 0,
  "videos": [],
  "image_count": 1,
  "images": [],
  "saved_count": 0,
  "collections_count": 0,
  "related_profiles": []
}